lightningtrace
