Metadata-Version: 1.1
Name: lightningtrace
Version: 0.1.2
Summary: Quickly contour a digital elevation model using rasterio and matplotlib
Home-page: https://github.com/GeomaticsResearch/lightningtrace
Author: Michael Ewald / GeomaticsResearch LLC
Author-email: mewald@geomaticsresearch.com
License: UNKNOWN
Download-URL: Where to download it.
Platform: UNKNOWN
Classifier: Development Status :: 3 - Alpha
Classifier: License :: OSI Approved :: MIT License
Classifier: Topic :: Scientific/Engineering
Classifier: Topic :: Scientific/Engineering :: GIS
Classifier: Topic :: Scientific/Engineering :: Visualization
Classifier: Intended Audience :: Developers
Classifier: Operating System :: MacOS :: MacOS X
Classifier: Operating System :: Microsoft :: Windows
Classifier: Operating System :: POSIX
Classifier: Programming Language :: Python
